polyforge/__init__.py
polyforge/metrics.py
polyforge/overlap.py
polyforge/pipeline.py
polyforge/process.py
polyforge/simplify.py
polyforge/tile.py
polyforge/topology.py
polyforge/clearance/__init__.py
polyforge/clearance/fix_clearance.py
polyforge/core/__init__.py
polyforge/core/cleanup.py
polyforge/core/constraints.py
polyforge/core/errors.py
polyforge/core/geometry_utils.py
polyforge/core/iterative_utils.py
polyforge/core/spatial_utils.py
polyforge/core/types.py
polyforge/merge/__init__.py
polyforge/merge/core.py
polyforge/ops/__init__.py
polyforge/ops/cleanup_ops.py
polyforge/ops/merge_boundary_extension.py
polyforge/ops/merge_common.py
polyforge/ops/merge_convex_bridges.py
polyforge/ops/merge_edge_detection.py
polyforge/ops/merge_ops.py
polyforge/ops/merge_selective_buffer.py
polyforge/ops/merge_simple_buffer.py
polyforge/ops/merge_vertex_movement.py
polyforge/ops/simplify_ops.py
polyforge/ops/clearance/__init__.py
polyforge/ops/clearance/holes.py
polyforge/ops/clearance/passages.py
polyforge/ops/clearance/protrusions.py
polyforge/ops/clearance/remove_protrusions.py
polyforge/ops/clearance/utils.py
polyforge/ops/merge/__init__.py
polyforge/repair/__init__.py
polyforge/repair/analysis.py
polyforge/repair/core.py
polyforge/repair/robust.py
polyforge/repair/utils.py
polyforge/repair/strategies/__init__.py
polyforge/repair/strategies/auto.py
polyforge/repair/strategies/buffer.py
polyforge/repair/strategies/reconstruct.py
polyforge/repair/strategies/simplify.py
polyforge/repair/strategies/strict.py
polyforge-0.1.0a1.dist-info/licenses/LICENSE
polyforge-0.1.0a1.dist-info/METADATA
polyforge-0.1.0a1.dist-info/WHEEL
polyforge-0.1.0a1.dist-info/top_level.txt
polyforge-0.1.0a1.dist-info/RECORD
